<University>
    <Students>
        <NO name="NO">1</NO>
        <StudentID name="StudentID">10000409</StudentID>
        <StudentName name="StudentName">M 5S Dilshanika Perera</StudentName>
    </Students>
    <Students>
        <NO name="NO">2</NO>
        <StudentID name="StudentID">10009301</StudentID>
        <StudentName name="StudentName">CW M A Shehan Abeyrathne</StudentName>
    </Students>
    <Students>
        <NO name="NO">3</NO>
        <StudentID name="StudentID">10009302</StudentID>
        <StudentName name="StudentName">BAKM Chithrananda</StudentName>
    </Students>
    <Students>
        <NO name="NO">4</NO>
        <StudentID name="StudentID">10009303</StudentID>
        <StudentName name="StudentName">W Shashini Minosha De Silva</StudentName>
    </Students>
    <Students>
        <NO name="NO">5</NO>
        <StudentID name="StudentID">10009304</StudentID>
        <StudentName name="StudentName">K L Udara Maduranga Liyanege</StudentName>
    </Students>
    <Students>
        <NO name="NO">6</NO>
        <StudentID name="StudentID">10009306</StudentID>
        <StudentName name="StudentName">Hansa Anuradha Wickramanayake</StudentName>
    </Students>
</University>